wilrise/__init__.py
wilrise/config.py
wilrise/context.py
wilrise/core.py
wilrise/errors.py
wilrise/extensions.py
wilrise/params.py
wilrise/protocol.py
wilrise/testing.py
wilrise-0.1.2.dist-info/WHEEL
wilrise-0.1.2.dist-info/METADATA
wilrise-0.1.2.dist-info/RECORD
