Metadata-Version: 2.3
Name: wilrise
Version: 0.1.2
Summary: A modern async JSON-RPC framework built on Starlette. Where determination rises from simplicity.
Keywords: json-rpc,rpc,starlette,asyncio,api
Author: William
Author-email: William <tkn17@qq.com>
License: MIT
Classifier: Development Status :: 4 - Beta
Classifier: Framework :: AsyncIO
Classifier: Intended Audience :: Developers
Classifier: License :: OSI Approved :: MIT License
Classifier: Programming Language :: Python :: 3
Classifier: Programming Language :: Python :: 3.12
Classifier: Programming Language :: Python :: 3.13
Classifier: Topic :: Internet :: WWW/HTTP
Requires-Dist: starlette>=0.41.0
Requires-Dist: uvicorn[standard]>=0.32.0
Requires-Dist: pydantic>=2.0.0 ; extra == 'pydantic'
Requires-Python: >=3.12
Provides-Extra: pydantic
